{
 "strong_keywords": ["telangana","hyderabad","warangal","nizamabad","karimnagar","secunderabad","medak","khammam","adilabad","kcr","ktr","brs","trs","Yadagirigutta","తెలంగాణ","హైదరాబాద్","హైద్రాబాద్","వరంగల్","నిజామాబాద్","కరీంనగర్","సికింద్రాబాద్","మెదక్","ఖమ్మం","ఆదిలాబాద్"],
  "districts": [
    { "en": "Adilabad", "te": "ఆదిలాబాద్" },
    { "en": "Kumuram Bheem Asifabad", "te": "కుమురం భీం ఆసిఫాబాద్" },
    { "en": "Mancherial", "te": "మంచెరియల్" },
    { "en": "Nirmal", "te": "నిర్మల్" },
    { "en": "Nizamabad", "te": "నిజామాబాద్" },
    { "en": "Jagtial", "te": "జగిత్యాల" },
    { "en": "Peddapalli", "te": "పెద్దపల్లి" },
    { "en": "Kamareddy", "te": "కామారెడ్డి" },
    { "en": "Rajanna Sircilla", "te": "రాజన్న సిరిసిల్ల జిల్లా" },
    { "en": "Karimnagar", "te": "కరీంనగర్" },
    { "en": "Jayashankar Bhupalpally", "te": "జయశంకర్ భూపాలపల్లి" },
    { "en": "Sangareddy", "te": "సంగారెడ్డి" },
    { "en": "Medak", "te": "మెదక్" },
    { "en": "Siddipet", "te": "సిద్దిపేట" },
    { "en": "Jangaon", "te": "జంగావ్" },
    { "en": "Hanumakonda", "te": "హనుమకొండ" },
    { "en": "Warangal", "te": "వరంగల్" },
    { "en": "Mulugu", "te": "ములుగు జిల్లా" },
    { "en": "Bhadradri Kothagudem", "te": "భద్రాద్రి కొత్తగూడెం" },
    { "en": "Khammam", "te": "ఖమ్మం" },
    { "en": "Mahabubabad", "te": "మహబూబాబాద్" },
    { "en": "Suryapet", "te": "సూర్యాపేట" },
    { "en": "Nalgonda", "te": "నల్గొండ" },
    { "en": "Yadadri Bhuvanagiri", "te": "యాదాద్రి భువనగిరి" },
    { "en": "Medchal-Malkajgiri", "te": "మేడ్చల్ మల్కాజిగిరి" },
    { "en": "Hyderabad", "te": "హైదరాబాద్" },
    { "en": "Ranga Reddy", "te": "రంగారెడ్డి జిల్లా" },
    { "en": "Vikarabad", "te": "వికారాబాద్" },
    { "en": "Narayanpet", "te": "నారాయణ పేట" },
    { "en": "Mahabubnagar", "te": "మహబూబ్ నగర్" },
    { "en": "Nagarkurnool", "te": "నాగర్ కర్నూల్ జిల్లా" },
    { "en": "Wanaparthy", "te": "వనపర్తి" },
    { "en": "Jogulamba Gadwal", "te": "జోగులాంబ గద్వాల" }
  ],

  "mandals": [
    { "en": "Tamsi", "te": "తాంసి" },
    { "en": "Talamadagu", "te": "తలమడగు" },
    { "en": "Sirikonda", "te": "సిరికొండ" },
    { "en": "Neradigonda", "te": "నేరాడిగొండ" },
    { "en": "Mavala", "te": "మావల" },
    { "en": "Jainad", "te": "జైనాద్" },
    { "en": "Ichoda", "te": "ఇచోడా" },
    { "en": "Gudihathnur", "te": "గూడిహత్నూర్" },
    { "en": "Bheempoor", "te": "భీంపూర్" },
    { "en": "Boath", "te": "బోథ్" },
    { "en": "Bela", "te": "బెలా" },
    { "en": "Adilabad Urban", "te": "ఆదిలాబాద్ పట్టణం" },
    { "en": "Adilabad Rural", "te": "ఆదిలాబాద్ గ్రామీణం" },
    { "en": "Utnoor", "te": "ఉట్నూర్" },
    { "en": "Narnoor", "te": "నార్నూర్" },
    { "en": "Inderavelly", "te": "ఇంద్రవెల్లి" },
    { "en": "Gadiguda", "te": "గాడిగూడ" },
    { "en": "Yellandu", "te": "యెల్లండు" },
    { "en": "Kothagudem", "te": "కోతగూడెం" },
    { "en": "Bhadrachalam", "te": "భద్రాచలం" },
    { "en": "Kazipet", "te": "కాజీపేట" },
    { "en": "Parkal", "te": "పార్కల్" },
    { "en": "Ameerpet", "te": "అమీర్పేట" },
    { "en": "Secunderabad", "te": "సికింద్రాబాద్" },
    { "en": "Khairtabad", "te": "ఖైరతాబాద్" },
    { "en": "Shamshabad", "te": "షామ్షాబాద్" }
  ],

  "political_parties": [
    { "en": "BRS", "te": "బీఆర్ఎస్" },
    { "en": "TRS", "te": "టీఆర్ఎస్" },
    { "en": "Bharat Rashtra Samithi", "te": "భారత్ రాష్ట్ర సమితి" },
    { "en": "Telangana Rashtra Samithi", "te": "తెలంగాణ రాష్ట్ర సమితి" },
    { "en": "TJS", "te": "టీజెఎస్" },
    { "en": "Telangana Jana Samithi", "te": "తెలంగాణ జన సమితి" },
    { "en": "AIMIM", "te": "ఏఐఎంఐఎం" },
    { "en": "MIM", "te": "ఎమ్మైఎం" },
    {
      "en": "Majlis-e-Ittehadul Muslimeen",
      "te": "మజ్లిస్ ఎ ఇత్తేహాదుల్ ముస్లిమీన్"
    },
    {
      "en": "All India Majlis-e-Ittehadul Muslimeen",
      "te": "అఖిల భారత మజ్లిస్ ఎ ఇత్తేహాదుల్ ముస్లిమీన్"
    }
  ],
 "places":[
    { "en": "Charminar", "te": "చార్మినార్", "location_en": "Hyderabad", "location_te": "హైదరాబాద్" },
    { "en": "Golconda Fort", "te": "గోల్కొండ కోట", "location_en": "Hyderabad", "location_te": "హైదరాబాద్" },
    { "en": "Chowmahalla Palace", "te": "చౌమహల్లా ప్యాలెస్", "location_en": "Hyderabad", "location_te": "హైదరాబాద్" },
    { "en": "Qutb Shahi Tombs", "te": "కుతుబ్ షాహీ సమాధులు", "location_en": "Hyderabad", "location_te": "హైదరాబాద్" },
    { "en": "Warangal Fort", "te": "వరంగల్ కోట", "location_en": "Warangal", "location_te": "వరంగల్" },
    { "en": "Bhongir Fort", "te": "భువనగిరి కోట", "location_en": "Bhongir", "location_te": "భువనగిరి" },
    { "en": "Ramappa Temple", "te": "రామప్ప దేవాలయం", "location_en": "Mulugu", "location_te": "ములుగు" },
    { "en": "Bhadrachalam Temple", "te": "భద్రాచలం ఆలయం", "location_en": "Bhadrachalam", "location_te": "భద్రాచలం" },
    { "en": "Yadagirigutta", "te": "యాదాద్రి ఆలయం", "location_en": "Yadadri", "location_te": "యాదాద్రి" },
    { "en": "Thousand Pillar Temple", "te": "వెయ్యి స్తంభాల ఆలయం", "location_en": "Hanumakonda", "location_te": "హనుమకొండ" },
    { "en": "Basara Saraswati Temple", "te": "బాసర సరస్వతి ఆలయం", "location_en": "Basara", "location_te": "బాసర" },
    { "en": "Ananthagiri Hills", "te": "అనంతగిరి కొండలు", "location_en": "Vikarabad", "location_te": "వికారాబాద్" },
    { "en": "Kuntala Waterfalls", "te": "కుంటాల జలపాతం", "location_en": "Adilabad", "location_te": "ఆదిలాబాద్" },
    { "en": "Bogatha Waterfalls", "te": "బొగత జలపాతం", "location_en": "Khammam", "location_te": "ఖమ్మం" },
    { "en": "Nagarjuna Sagar Dam", "te": "నాగార్జున సాగర్ డ్యాం", "location_en": "Nalgonda", "location_te": "నల్గొండ" },
    { "en": "Ramoji Film City", "te": "రామోజీ ఫిల్మ్ సిటీ", "location_en": "Hyderabad", "location_te": "హైదరాబాద్" },
    { "en": "Taj Falaknuma Palace", "te": "తాజ్ ఫలక్నుమా ప్యాలెస్", "location_en": "Hyderabad", "location_te": "హైదరాబాద్" },
    { "en": "Medak Cathedral & Fort", "te": "మెదక్ చర్చి మరియు కోట", "location_en": "Medak", "location_te": "మెదక్" },
    { "en": "Siddulagutta", "te":"సిద్ధులగుట్ట‌","location_en": "Siddulagutta", "location_te": "సిద్ధులగుట్"}, 
  {"name_en": "Charminar", "name_te": "చార్మినార్", "location_en": "Hyderabad", "location_te": "హైదరాబాద్", "description_en": "16th-century mosque and monument; global icon of Hyderabad.", "description_te": "16వ శతాబ్దపు కట్టడం; హైదరాబాద్ నగరానికి ప్రధాన చిహ్నం."},
  {"name_en": "Golconda Fort", "name_te": "గోల్కొండ కోట", "location_en": "Hyderabad", "location_te": "హైదరాబాద్", "description_en": "Majestic citadel known for acoustics and diamond trade history.", "description_te": "శబ్ద తరంగాల వింతలకు మరియు వజ్రాల వ్యాపారానికి ప్రసిద్ధి."},
  {"name_en": "Warangal Fort", "name_te": "వరంగల్ కోట", "location_en": "Warangal", "location_te": "వరంగల్", "description_en": "13th-century Kakatiya capital featuring iconic stone gateways.", "description_te": "కాకతీయుల కాలం నాటి కోట మరియు ప్రసిద్ధ శిలా తోరణాలు."},
  {"name_en": "Yadadri Temple", "name_te": "యాదాద్రి లక్ష్మీనరసింహ స్వామి ఆలయం", "location_en": "Yadadri Bhuvanagiri", "location_te": "యాదాద్రి భువనగిరి", "description_en": "Major cave temple of Lord Narasimha, recently renovated.", "description_te": "శ్రీ లక్ష్మీనరసింహ స్వామి కొలువై ఉన్న పుణ్యక్షేత్రం."},
  {"name_en": "Ramappa Temple", "name_te": "రామప్ప దేవాలయం", "location_en": "Mulugu", "location_te": "ములుగు", "description_en": "UNESCO site famous for floating bricks and Kakatiya art.", "description_te": "నీటిపై తేలే ఇటుకలు గల యునెస్కో ప్రపంచ వారసత్వ కట్టడం."},
  {"name_en": "Bhadrachalam Temple", "name_te": "భద్రాచలం శ్రీ సీతారామచంద్ర స్వామి ఆలయం", "location_en": "Bhadradri Kothagudem", "location_te": "భద్రాద్రి కొత్తగూడెం", "description_en": "Sacred site for Lord Rama on the banks of River Godavari.", "description_te": "గోదావరి తీరాన ఉన్న పవిత్ర శ్రీరామ క్షేత్రం."},
  {"name_en": "Basar Saraswati Temple", "name_te": "బాసర జ్ఞాన సరస్వతీ ఆలయం", "location_en": "Nirmal", "location_te": "నిర్మల్", "description_en": "One of India's few temples dedicated to Goddess Saraswati.", "description_te": "భారతదేశంలోని అతికొద్ది సరస్వతీ ఆలయాలలో ఒకటి."},
  {"name_en": "Thousand Pillar Temple", "name_te": "వేయి స్తంభాల గుడి", "location_en": "Hanamkonda", "location_te": "హన్మకొండ", "description_en": "Architectural marvel dedicated to Shiva, Vishnu, and Surya.", "description_te": "శివుడు, విష్ణువు మరియు సూర్యునికి అంకితం చేసిన గుడి."},
  {"name_en": "Kuntala Waterfalls", "name_te": "కుంతల జలపాతం", "location_en": "Adilabad", "location_te": "ఆదిలాబాద్", "description_en": "Highest waterfall in Telangana at 150 feet height.", "description_te": "రాష్ట్రంలోనే అతి ఎత్తైన జలపాతం."},
  {"name_en": "Ananthagiri Hills", "name_te": "అనంతగిరి కొండలు", "location_en": "Vikarabad", "location_te": "వికారాబాద్", "description_en": "Popular trekking spot and source of River Musi.", "description_te": "ట్రెకింగ్ కి ప్రసిద్ధి మరియు మూసీ నది జన్మస్థలం."},
  {"name_en": "Bogatha Waterfalls", "name_te": "బొగత జలపాతం", "location_en": "Mulugu", "location_te": "ములుగు", "description_en": "Known as the 'Niagara of Telangana'.", "description_te": "తెలంగాణ నయాగరాగా పిలువబడే అందమైన జలపాతం."},
  {"name_en": "Laknavaram Lake", "name_te": "లక్నవరం చెరువు", "location_en": "Mulugu", "location_te": "ములుగు", "description_en": "Scenic lake with a 160-meter suspension bridge.", "description_te": "వేలాడే వంతెనకు ప్రసిద్ధి చెందిన ప్రకృతి సిద్ధమైన సరస్సు."},
  {"name_en": "Nagarjuna Sagar Dam", "name_te": "నాగార్జున సాగర్ ఆనకట్ట", "location_en": "Nalgonda", "location_te": "నల్గొండ", "description_en": "World's largest masonry dam on the Krishna River.", "description_te": "కృష్ణా నదిపై నిర్మించిన భారీ ఆనకట్ట."},
  {"name_en": "Ramoji Film City", "name_te": "రామోజీ ఫిలిం సిటీ", "location_en": "Hyderabad", "location_te": "హైదరాబాద్", "description_en": "World's largest film studio complex.", "description_te": "ప్రపంచంలోనే అతిపెద్ద ఫిల్మ్ స్టూడియో కాంప్లెక్స్."},
  {"name_en": "Hussain Sagar Lake", "name_te": "హుస్సేన్ సాగర్", "location_en": "Hyderabad", "location_te": "హైదరాబాద్", "description_en": "Heart-shaped lake with a monolithic Buddha statue.", "description_te": "మధ్యలో భారీ బుద్ధ విగ్రహం ఉన్న సరస్సు."},
  {"name_en": "Salar Jung Museum", "name_te": "సాలార్ జంగ్ మ్యూజియం", "location_en": "Hyderabad", "location_te": "హైదరాబాద్", "description_en": "One of the largest antique collections in India.", "description_te": "భారతదేశంలోని అతిపెద్ద పురాతన వస్తు ప్రదర్శనశాల."},
  {"name_en": "Statue of Equality", "name_te": "సమతా మూర్తి", "location_en": "Muchintal", "location_te": "ముచ్చింతల్", "description_en": "Giant statue of Saint Ramanujacharya.", "description_te": "శ్రీ రామానుజాచార్యుల భారీ విగ్రహం."},
  {"name_en": "Qutb Shahi Tombs", "name_te": "కుతుబ్ షాహీ సమాధులు", "location_en": "Hyderabad", "location_te": "హైదరాబాద్", "description_en": "Royal necropolis of the Golconda rulers with Persian architecture.", "description_te": "గోల్కొండ పాలకుల సమాధులు; పర్షియన్ శిల్పకళా చాతుర్యం."},
  {"name_en": "Medak Cathedral", "name_te": "మెదక్ చర్చి", "location_en": "Medak", "location_te": "మెదక్", "description_en": "Largest church in Telangana, built in Gothic style.", "description_te": "దక్షిణ భారతదేశంలోనే అతిపెద్ద గోతిక్ తరహా చర్చి."},
  {"name_en": "Alampur Jogulamba Temple", "name_te": "అలంపూర్ జోగులాంబ దేవాలయం", "location_en": "Gadwal", "location_te": "గద్వాల", "description_en": "One of the 18 Shakti Peethas and entrance to Srisailam.", "description_te": "అష్టాదశ శక్తి పీఠాలలో ఒకటి."}
]
}
